martian/__init__.py
martian/__main__.py
martian/_base_client.py
martian/_client.py
martian/_compat.py
martian/_constants.py
martian/_exceptions.py
martian/_files.py
martian/_models.py
martian/_module_client.py
martian/_qs.py
martian/_resource.py
martian/_response.py
martian/_streaming.py
martian/_types.py
martian/_version.py
martian/pagination.py
martian/py.typed
martian/version.py
martian/_extras/__init__.py
martian/_extras/_common.py
martian/_extras/numpy_proxy.py
martian/_extras/pandas_proxy.py
martian/_utils/__init__.py
martian/_utils/_logs.py
martian/_utils/_proxy.py
martian/_utils/_transform.py
martian/_utils/_utils.py
martian/cli/__init__.py
martian/cli/_cli.py
martian/cli/_errors.py
martian/cli/_models.py
martian/cli/_progress.py
martian/cli/_utils.py
martian/cli/_api/__init__.py
martian/cli/_api/_main.py
martian/cli/_api/audio.py
martian/cli/_api/completions.py
martian/cli/_api/files.py
martian/cli/_api/image.py
martian/cli/_api/models.py
martian/cli/_api/chat/__init__.py
martian/cli/_api/chat/completions.py
martian/cli/_tools/__init__.py
martian/cli/_tools/_main.py
martian/cli/_tools/fine_tunes.py
martian/cli/_tools/migrate.py
martian/lib/_old_api.py
martian/lib/_validators.py
martian/lib/azure.py
martian/resources/__init__.py
martian/resources/completions.py
martian/resources/edits.py
martian/resources/embeddings.py
martian/resources/files.py
martian/resources/fine_tunes.py
martian/resources/images.py
martian/resources/models.py
martian/resources/moderations.py
martian/resources/audio/__init__.py
martian/resources/audio/audio.py
martian/resources/audio/speech.py
martian/resources/audio/transcriptions.py
martian/resources/audio/translations.py
martian/resources/beta/__init__.py
martian/resources/beta/beta.py
martian/resources/beta/assistants/__init__.py
martian/resources/beta/assistants/assistants.py
martian/resources/beta/assistants/files.py
martian/resources/beta/threads/__init__.py
martian/resources/beta/threads/threads.py
luka_openai-1.2.9.dist-info/METADATA
luka_openai-1.2.9.dist-info/WHEEL
luka_openai-1.2.9.dist-info/entry_points.txt
luka_openai-1.2.9.dist-info/licenses/LICENSE
luka_openai-1.2.9.dist-info/RECORD
